lsm_tool.py
lsm/__init__.py
lsm/_lsm.cp311-win_amd64.pyd
lsm/_lsm.pyi
lsm/py.typed
lsm-0.5.10.dist-info/LICENSE
lsm-0.5.10.dist-info/METADATA
lsm-0.5.10.dist-info/WHEEL
lsm-0.5.10.dist-info/entry_points.txt
lsm-0.5.10.dist-info/top_level.txt
lsm-0.5.10.dist-info/RECORD
