Metadata-Version: 2.1
Name: lsm
Version: 0.5.10
Summary: Python bindings for SQLite's LSM key/value engine
Home-page: https://github.com/mosquito/python-lsm/
Author: Dmitry Orlov
Author-email: me@mosquito.su
License: Apache Software License
Project-URL: Documentation, https://github.com/mosquito/python-lsm/
Project-URL: Source, https://github.com/mosquito/python-lsm/
Project-URL: Tracker, https://github.com/mosquito/python-lsm/issues
Project-URL: Say Thanks!, https://saythanks.io/to/mosquito
Platform: UNKNOWN
Classifier: Intended Audience :: Developers
Classifier: License :: OSI Approved :: Apache Software License
Classifier: Natural Language :: English
Classifier: Operating System :: MacOS
Classifier: Operating System :: Microsoft
Classifier: Operating System :: POSIX
Classifier: Programming Language :: Python :: 3
Classifier: Programming Language :: Python :: 3.9
Classifier: Programming Language :: Python :: 3.10
Classifier: Programming Language :: Python :: 3.11
Classifier: Programming Language :: Python :: 3.12
Classifier: Programming Language :: Python :: 3.13
Classifier: Programming Language :: Python :: Implementation :: CPython
Classifier: Programming Language :: Python
Classifier: Topic :: Database :: Database Engines/Servers
Classifier: Topic :: Database
Classifier: Topic :: Software Development :: Libraries
Classifier: Topic :: Software Development
Classifier: Typing :: Typed
Requires-Python: >=3.9,<4
License-File: LICENSE
Provides-Extra: develop
Requires-Dist: pytest; extra == "develop"
Requires-Dist: pytest-subtests; extra == "develop"
Requires-Dist: markdown-pytest>=0.3.0; extra == "develop"
